proper_tea/__init__.py
proper_tea/_version.py
proper_tea/constrained_numbers.py
proper_tea/discrete_sets.py
proper_tea/property_factory.py
proper_tea/numpy/__init__.py
proper_tea/numpy/numpy_arrays.py
proper_tea-0.3.4.dist-info/LICENSE.txt
proper_tea-0.3.4.dist-info/METADATA
proper_tea-0.3.4.dist-info/WHEEL
proper_tea-0.3.4.dist-info/top_level.txt
proper_tea-0.3.4.dist-info/RECORD
