Metadata-Version: 2.1
Name: proper-tea
Version: 0.3.4
Summary: A Python package for automating the creation of common class properties
Home-page: https://github.com/LiamPattinson/proper_tea
Author: Liam Pattinson
Author-email: liampattinson@gmail.com
License: MIT
Project-URL: Source, https://github.com/LiamPattinson/proper_tea
Project-URL: Tracker, https://github.com/LiamPattinson/proper_tea/issues
Platform: UNKNOWN
Classifier: Natural Language :: English
Classifier: Topic :: Software Development :: Libraries
Classifier: Topic :: Utilities
Classifier: Programming Language :: Python :: 3
Classifier: Programming Language :: Python :: 3.7
Classifier: Programming Language :: Python :: 3.8
Classifier: Programming Language :: Python :: 3.9
Classifier: Programming Language :: Python :: 3.10
Classifier: License :: OSI Approved :: MIT License
Classifier: Operating System :: OS Independent
Requires-Python: >=3.7
License-File: LICENSE.txt
Requires-Dist: importlib-metadata ; python_version < "3.8"
Provides-Extra: tests
Requires-Dist: pytest (>=5.4.3) ; extra == 'tests'
Requires-Dist: numpy (>=1.20.0) ; extra == 'tests'
